sahagun/__init__.py
sahagun/validacion_construcciones.py
sahagun/validacion_terrenos.py
sahagun/validacion_unidades.py
sahagun-0.1.dist-info/METADATA
sahagun-0.1.dist-info/WHEEL
sahagun-0.1.dist-info/top_level.txt
sahagun-0.1.dist-info/RECORD
